needle_haystack/__init__.py
needle_haystack/document_store.py
needle_haystack/needle_embedding_retriever.py
needle_haystack_ai-0.1.0.dist-info/LICENSE
needle_haystack_ai-0.1.0.dist-info/METADATA
needle_haystack_ai-0.1.0.dist-info/WHEEL
needle_haystack_ai-0.1.0.dist-info/RECORD
