Metadata-Version: 2.1
Name: needle-haystack-ai
Version: 0.1.0
Summary: Needle RAG tools for Haystack
License: MIT
Keywords: needle,api,retrieval-augmented generation,rag,information-retrieval,artificial intelligence,ai
Author: Onur Eken
Author-email: m.onureken@gmail.com
Requires-Python: >=3.9,<4.0
Classifier: Development Status :: 4 - Beta
Classifier: Intended Audience :: Developers
Classifier: License :: OSI Approved :: MIT License
Classifier: Operating System :: OS Independent
Classifier: Programming Language :: Python :: 3
Classifier: Programming Language :: Python :: 3.9
Classifier: Programming Language :: Python :: 3.10
Classifier: Programming Language :: Python :: 3.11
Classifier: Programming Language :: Python :: 3.12
Classifier: Topic :: Scientific/Engineering :: Artificial Intelligence
Classifier: Topic :: Software Development :: Libraries :: Python Modules
Requires-Dist: haystack-ai (>=2.4.0,<3.0.0)
Requires-Dist: needle-python (>=0.3.0,<0.4.0)
Project-URL: documentation, https://docs.needle-ai.com
Project-URL: homepage, https://needle-ai.com
Project-URL: issues, https://github.com/JANHMS/needle-haystack/issues
Project-URL: repository, https://github.com/JANHMS/needle-haystack
